README.txt
bootstrap.py
buildout.cfg
setup.py
versions.cfg
collective/__init__.py
collective.piwik.now.egg-info/PKG-INFO
collective.piwik.now.egg-info/SOURCES.txt
collective.piwik.now.egg-info/dependency_links.txt
collective.piwik.now.egg-info/entry_points.txt
collective.piwik.now.egg-info/namespace_packages.txt
collective.piwik.now.egg-info/not-zip-safe
collective.piwik.now.egg-info/requires.txt
collective.piwik.now.egg-info/top_level.txt
collective/piwik/__init__.py
collective/piwik/now/__init__.py
collective/piwik/now/configure.zcml
collective/piwik/now/onlineusers.pt
collective/piwik/now/onlineusers.py
collective/piwik/now/version.txt
collective/piwik/now/profiles/default/metadata.xml
collective/piwik/now/profiles/default/portlets.xml
collective/piwik/now/tests/__init__.py
collective/piwik/now/tests/base.py
collective/piwik/now/tests/test_portlet.py
docs/CONTRIBUTORS.txt
docs/HISTORY.txt
docs/INSTALL.txt
docs/LICENSE.GPL
docs/LICENSE.txt