Metadata-Version: 1.0
Name: collective.piwik.now
Version: 0.1
Summary: A portlet that uses the Piwik open source analytics system to display how many people are using your Plone site at the moment
Home-page: http://svn.plone.org/svn/collective/
Author: UNKNOWN
Author-email: UNKNOWN
License: GPL
Platform: UNKNOWN
Classifier: Framework :: Plone
Classifier: Programming Language :: Python
